schematics/__init__.py
schematics/common.py
schematics/datastructures.py
schematics/exceptions.py
schematics/iteration.py
schematics/models.py
schematics/role.py
schematics/schema.py
schematics/transforms.py
schematics/translator.py
schematics/undefined.py
schematics/util.py
schematics/validate.py
schematics/contrib/__init__.py
schematics/contrib/enum_type.py
schematics/contrib/machine.py
schematics/contrib/mongo.py
schematics/locale/schematics.pot
schematics/locale/pt_BR/LC_MESSAGES/schematics.po
schematics/types/__init__.py
schematics/types/base.py
schematics/types/compound.py
schematics/types/net.py
schematics/types/serializable.py
schematics/types/union.py
schematics_py310_plus-0.0.4.dist-info/LICENSE
schematics_py310_plus-0.0.4.dist-info/WHEEL
schematics_py310_plus-0.0.4.dist-info/METADATA
schematics_py310_plus-0.0.4.dist-info/RECORD
