Metadata-Version: 2.1
Name: schematics-py310-plus
Version: 0.0.4
Summary: Forked from schematics/schematics: Python Data Structures for Humans, supporting python 3.10 plus.
Author-email: James Dennis <jdennis@gmail.com>, Jóhann Þorvaldur Bergþórsson <johann@plainvanillagames.com>, Jökull Sólberg <jokull@plainvanillagames.com>, Kalle Tuure <kalle@goodtimes.fi>, Kirk Strauser <kirk@strauser.com>, Paul Eipper <paul@nkey.com.br>
Classifier: Intended Audience :: Developers
Classifier: License :: OSI Approved :: BSD License
Classifier: Programming Language :: Python
Classifier: Programming Language :: Python :: 3
Classifier: Programming Language :: Python :: 3.9
Classifier: Programming Language :: Python :: 3.10
Classifier: Programming Language :: Python :: 3.11
Project-URL: Docs, http://schematics.readthedocs.org/
Project-URL: Home, http://github.com/averagechris/schematics/
